recon_sentinel/__init__.py
recon_sentinel/cli.py
recon_sentinel/render.py
recon_sentinel/rules_loader.py
recon_sentinel/scope.py
recon_sentinel/utils.py
recon_sentinel/libs/__init__.py
recon_sentinel/libs/librdirbuster.so
recon_sentinel/libs/librpscan.so
recon_sentinel/libs/libtinyxml2.so
recon_sentinel/libs/libtinyxml2.so.11
recon_sentinel/libs/libtinyxml2.so.11.0.0
recon_sentinel/modules/ct.py
recon_sentinel/modules/dns.py
recon_sentinel/modules/librdirbuster.py
recon_sentinel/modules/librpscan.py
recon_sentinel/rules/recon_rules.yaml
recon_sentinel/templates/casefile.md.j2
reconsentinel-1.0.1.dist-info/licenses/LICENSE
reconsentinel-1.0.1.dist-info/METADATA
reconsentinel-1.0.1.dist-info/WHEEL
reconsentinel-1.0.1.dist-info/entry_points.txt
reconsentinel-1.0.1.dist-info/top_level.txt
reconsentinel-1.0.1.dist-info/RECORD
