Metadata-Version: 2.4
Name: reconsentinel
Version: 1.0.1
Summary: Security reconnaissance toolkit: passive-first OSINT with active scanning capabilities (port scanning, DirBuster). Scope-aware with explainable findings.
Author: knightsky-cpu, mintRaven-05, ImonChakraborty
Author-email: Serene-Brew Team <serene.brew.git@gmail.com>
License: BSD-3-Clause
Project-URL: Homepage, https://github.com/serene-brew/ReconSentinel
Project-URL: Documentation, https://github.com/serene-brew/ReconSentinel#readme
Project-URL: Repository, https://github.com/serene-brew/ReconSentinel
Project-URL: Issues, https://github.com/serene-brew/ReconSentinel/issues
Keywords: security,reconnaissance,osint,port-scanning,dirbuster,pentesting
Classifier: Development Status :: 4 - Beta
Classifier: Intended Audience :: Information Technology
Classifier: Intended Audience :: System Administrators
Classifier: Topic :: Security
Classifier: Topic :: System :: Networking
Classifier: License :: OSI Approved :: BSD License
Classifier: Programming Language :: Python :: 3
Classifier: Programming Language :: Python :: 3.10
Classifier: Programming Language :: Python :: 3.11
Classifier: Programming Language :: Python :: 3.12
Classifier: Programming Language :: Python :: 3.13
Classifier: Operating System :: POSIX :: Linux
Classifier: Operating System :: MacOS
Requires-Python: >=3.10
License-File: LICENSE
Requires-Dist: typer>=0.12
Requires-Dist: PyYAML>=6
Requires-Dist: requests>=2.32
Requires-Dist: dnspython>=2.6.1
Requires-Dist: jinja2>=3.1
Requires-Dist: rich>=13.7
Requires-Dist: tldextract>=3.4
Dynamic: license-file
